[
  {
    "type": "Ground",
    "z_index": 0,
    "position": { "x": 0, "y": 0 }
  },
  {
    "type": "Ground",
    "z_index": 0,
    "position": { "x": 6, "y": 2 }
  },
  {
    "type": "Ground",
    "z_index": 0,
    "position": { "x": 7, "y": 2 }
  },
  {
    "type": "Ground",
    "z_index": 0,
    "position": { "x": 8, "y": 2 }
  },
  {
    "type": "Ground",
    "z_index": 0,
    "position": { "x": 10, "y": 4 }
  },
  {
    "type": "Fox",
    "z_index": 1,
    "position": { "x": 10, "y": 4 },
    "transform": {
      "size": { "x": 300, "y": 300 },
      "flip_x": true,
      "flip_y": true,
      "angle": 150
    }
  }
]
